caesar_cipher_tool_pye_edition/__init__.py
caesar_cipher_tool_pye_edition/main.py
caesar_cipher_tool_pye_edition-3.1.dist-info/LICENSE
caesar_cipher_tool_pye_edition-3.1.dist-info/METADATA
caesar_cipher_tool_pye_edition-3.1.dist-info/WHEEL
caesar_cipher_tool_pye_edition-3.1.dist-info/entry_points.txt
caesar_cipher_tool_pye_edition-3.1.dist-info/top_level.txt
caesar_cipher_tool_pye_edition-3.1.dist-info/RECORD
