Metadata-Version: 2.2
Name: caesar_cipher_tool_pye_edition
Version: 3.1
Summary: A simple terminal program use to encipher/decipher text to/from Caesar Cipher.
Home-page: https://github.com/uwungu01-rep/caesar-cipher-tool-python.edition
Author: Zizel
Author-email: danbua999@gmail.com
Classifier: Programming Language :: Python :: 3
Classifier: Operating System :: OS Independent
Classifier: License :: OSI Approved :: GNU General Public License v3 (GPLv3)
License-File: LICENSE
Dynamic: author
Dynamic: author-email
Dynamic: classifier
Dynamic: description
Dynamic: description-content-type
Dynamic: home-page
Dynamic: summary
